kmRead/__init__.py
kmRead/kmRead.py
kmRead-0.1.8.dist-info/METADATA
kmRead-0.1.8.dist-info/WHEEL
kmRead-0.1.8.dist-info/entry_points.txt
kmRead-0.1.8.dist-info/top_level.txt
kmRead-0.1.8.dist-info/RECORD
